serenity_sdk/__init__.py
serenity_sdk/auth.py
serenity_sdk/config.py
serenity_sdk/widgets.py
serenity_sdk/api/__init__.py
serenity_sdk/api/account.py
serenity_sdk/api/analytics.py
serenity_sdk/api/core.py
serenity_sdk/api/model.py
serenity_sdk/api/portfolio.py
serenity_sdk/api/pricing.py
serenity_sdk/api/provider.py
serenity_sdk/api/refdata.py
serenity_sdk/api/risk.py
serenity_sdk/api/risk_analytics.py
serenity_sdk/api/scenarios.py
serenity_sdk/api/storage.py
serenity_sdk/api/valuation.py
serenity_sdk/client/__init__.py
serenity_sdk/client/auth.py
serenity_sdk/client/auth0_client_cred_auth.py
serenity_sdk/client/auth0_device_auth.py
serenity_sdk/client/base_auth.py
serenity_sdk/client/config.py
serenity_sdk/client/raw.py
serenity_sdk/renderers/__init__.py
serenity_sdk/renderers/table.py
serenity_sdk/renderers/asset_search/__init__.py
serenity_sdk/renderers/asset_search/result_views.py
serenity_sdk/renderers/derivatives/__init__.py
serenity_sdk/renderers/derivatives/converters.py
serenity_sdk/renderers/derivatives/market_data.py
serenity_sdk/renderers/derivatives/option_finders.py
serenity_sdk/renderers/derivatives/overrides.py
serenity_sdk/renderers/derivatives/reference_data.py
serenity_sdk/renderers/derivatives/request_helpers.py
serenity_sdk/renderers/derivatives/table_plot.py
serenity_sdk/renderers/derivatives/utils.py
serenity_sdk/renderers/derivatives/widget_tools.py
serenity_sdk/renderers/risk_measures/__init__.py
serenity_sdk/renderers/shared/__init__.py
serenity_sdk/renderers/shared/dropdown_select.py
serenity_sdk/renderers/shared/simple_widgets.py
serenity_sdk/renderers/shared/utils.py
serenity_sdk/types/__init__.py
serenity_sdk/types/common.py
serenity_sdk/types/core.py
serenity_sdk/types/factors.py
serenity_sdk/types/measures.py
serenity_sdk/types/model.py
serenity_sdk/types/refdata.py
serenity_sdk/types/valuation.py
serenity_types/__init__.py
serenity_types/account/__init__.py
serenity_types/account/core.py
serenity_types/catalog/__init__.py
serenity_sdk_python-1.1.0.dist-info/LICENSE
serenity_sdk_python-1.1.0.dist-info/METADATA
serenity_sdk_python-1.1.0.dist-info/WHEEL
serenity_sdk_python-1.1.0.dist-info/top_level.txt
serenity_sdk_python-1.1.0.dist-info/RECORD
