Metadata-Version: 2.1
Name: serenity-sdk-python
Version: 1.1.0
Summary: Python SDK for the Serenity digital asset risk API
Home-page: http://cloudwall.tech
Author: Cloudwall DevSecOps team
Author-email: devsecops@cloudwall.tech
Requires-Python: >=3.8
License-File: LICENSE
Requires-Dist: auth0-python <4.5.0,>=4.4.2
Requires-Dist: bidict ==0.22.1
Requires-Dist: fire ==0.4.0
Requires-Dist: humps ==0.2.2
Requires-Dist: pandas ==1.5.3
Requires-Dist: plotly ==5.18.0
Requires-Dist: pyarrow ==14.0.1
Requires-Dist: pydantic ==1.10.13
Requires-Dist: requests ==2.31.0
Requires-Dist: scipy ==1.9.3
Requires-Dist: seaborn ==0.11.2
Requires-Dist: typing-extensions ==4.8.0
